asm_py/__init__.py
asm_py/core.py
asm_py/helpers.py
asm_py/parsers.py
asm_chill_py-0.1.0.dist-info/METADATA
asm_chill_py-0.1.0.dist-info/WHEEL
asm_chill_py-0.1.0.dist-info/top_level.txt
asm_chill_py-0.1.0.dist-info/RECORD
